gor/__init__.py
gor/asyncio_impl.py
gor/base.py
gor/middleware.py
gor/multiprocess_impl.py
gor/version.py
gor-0.2.3.dist-info/LICENSE
gor-0.2.3.dist-info/METADATA
gor-0.2.3.dist-info/WHEEL
gor-0.2.3.dist-info/top_level.txt
gor-0.2.3.dist-info/RECORD
