Metadata-Version: 2.1
Name: gor
Version: 0.2.3
Summary: Python library for GoReplay Middleware
Home-page: http://github.com/amyangfei/GorMW
Author: Yang Fei
Author-email: amyangfei@gmail.com
Maintainer: Yang Fei
Maintainer-email: amyangfei@gmail.com
License: MIT
Keywords: GoReplay Middleware
Platform: UNKNOWN
